txmusicbrainz/__init__.py
txmusicbrainz/_entities.py
txmusicbrainz/client.py
txmusicbrainz/tests/__init__.py
txmusicbrainz/tests/test_client.py
txmusicbrainz-0.1.0.dist-info/DESCRIPTION.rst
txmusicbrainz-0.1.0.dist-info/METADATA
txmusicbrainz-0.1.0.dist-info/metadata.json
txmusicbrainz-0.1.0.dist-info/RECORD
txmusicbrainz-0.1.0.dist-info/top_level.txt
txmusicbrainz-0.1.0.dist-info/WHEEL
