Metadata-Version: 2.0
Name: txmusicbrainz
Version: 0.1.0
Summary: Twisted API client for the MusicBrainz API
Home-page: https://github.com/Julian/txmusicbrainz
Author: Julian Berman
Author-email: Julian@GrayVines.com
License: MIT
Platform: UNKNOWN
Classifier: Development Status :: 3 - Alpha
Classifier: License :: OSI Approved :: MIT License
Classifier: Operating System :: OS Independent
Classifier: Programming Language :: Python
Classifier: Programming Language :: Python :: 2.6
Classifier: Programming Language :: Python :: 2.7
Classifier: Programming Language :: Python :: 2
Classifier: Programming Language :: Python :: Implementation :: CPython
Classifier: Programming Language :: Python :: Implementation :: PyPy
